jolted_mod/LLM_service.py
jolted_mod/__init__.py
jolted_mod/block.py
jolted_mod/block_factory.py
jolted_mod/cell_type.py
jolted_mod/config.py
jolted_mod/content_generator.py
jolted_mod/fastapi_python.ipynb
jolted_mod/intro_loops_python.html
jolted_mod/intro_loops_python.ipynb
jolted_mod/intro_loops_python_files/libs/bootstrap/bootstrap-icons.css
jolted_mod/intro_loops_python_files/libs/bootstrap/bootstrap-icons.woff
jolted_mod/intro_loops_python_files/libs/bootstrap/bootstrap.min.css
jolted_mod/intro_loops_python_files/libs/bootstrap/bootstrap.min.js
jolted_mod/intro_loops_python_files/libs/clipboard/clipboard.min.js
jolted_mod/intro_loops_python_files/libs/quarto-html/anchor.min.js
jolted_mod/intro_loops_python_files/libs/quarto-html/popper.min.js
jolted_mod/intro_loops_python_files/libs/quarto-html/quarto-syntax-highlighting.css
jolted_mod/intro_loops_python_files/libs/quarto-html/quarto.js
jolted_mod/intro_loops_python_files/libs/quarto-html/tippy.css
jolted_mod/intro_loops_python_files/libs/quarto-html/tippy.umd.min.js
jolted_mod/main.py
jolted_mod/module_types.py
jolted_mod/nosql_mongo_gpt4.ipynb
jolted_mod/quarto.html
jolted_mod/quarto.ipynb
jolted_mod/quarto_files/libs/bootstrap/bootstrap-icons.css
jolted_mod/quarto_files/libs/bootstrap/bootstrap-icons.woff
jolted_mod/quarto_files/libs/bootstrap/bootstrap.min.css
jolted_mod/quarto_files/libs/bootstrap/bootstrap.min.js
jolted_mod/quarto_files/libs/clipboard/clipboard.min.js
jolted_mod/quarto_files/libs/quarto-html/anchor.min.js
jolted_mod/quarto_files/libs/quarto-html/popper.min.js
jolted_mod/quarto_files/libs/quarto-html/quarto-syntax-highlighting.css
jolted_mod/quarto_files/libs/quarto-html/quarto.js
jolted_mod/quarto_files/libs/quarto-html/tippy.css
jolted_mod/quarto_files/libs/quarto-html/tippy.umd.min.js
jolted_mod/react_typescript.ipynb
jolted_mod/template_generator.py
jolted_mod/tutorial_template.json
joltedmod-0.2.4.dist-info/LICENSE
joltedmod-0.2.4.dist-info/METADATA
joltedmod-0.2.4.dist-info/WHEEL
joltedmod-0.2.4.dist-info/entry_points.txt
joltedmod-0.2.4.dist-info/RECORD
