Metadata-Version: 2.1
Name: joltedmod
Version: 0.2.4
Summary: JoltEd self-documenting learning module
License: MIT
Author: Nathan Laundry
Requires-Python: >=3.9,<4.0
Classifier: License :: OSI Approved :: MIT License
Classifier: Programming Language :: Python :: 3
Classifier: Programming Language :: Python :: 3.9
Classifier: Programming Language :: Python :: 3.10
Classifier: Programming Language :: Python :: 3.11
Requires-Dist: aiofiles (>=23.1.0,<24.0.0)
Requires-Dist: alive-progress (>=3.1.3,<4.0.0)
Requires-Dist: colorama (>=0.4.6,<0.5.0)
Requires-Dist: markdown2 (>=2.4.8,<3.0.0)
Requires-Dist: markdownify (>=0.11.6,<0.12.0)
Requires-Dist: nbf (>=0.0.5,<0.0.6)
Requires-Dist: nbformat (>=5.8.0,<6.0.0)
Requires-Dist: openai (>=0.27.7,<0.28.0)
Requires-Dist: pydantic (>=1.10.9,<2.0.0)
Requires-Dist: tqdm (>=4.65.0,<5.0.0)
